yag_slam_cpp.cpython-310-x86_64-linux-gnu.so
yag_slam-0.2.5.dist-info/WHEEL
yag_slam-0.2.5.dist-info/LICENSE
yag_slam-0.2.5.dist-info/top_level.txt
yag_slam-0.2.5.dist-info/RECORD
yag_slam-0.2.5.dist-info/METADATA
yag_slam/models.py
yag_slam/splicing.py
yag_slam/__init__.py
yag_slam/helpers.py
yag_slam/graph_slam.py
yag_slam/serde.py
yag_slam/scan_matching.py
yag_slam/graph.py
yag_slam/raytracing.py
yag_slam-0.2.5.data/scripts/slam_node_ros1
