Metadata-Version: 2.1
Name: yag-slam
Version: 0.2.5
Summary: A complete 2D and 3D graph SLAM implementation using plagiarized code from SRI's OpenKarto
Home-page: UNKNOWN
Author: Jariullah Safi
Author-email: safijari@isu.edu
License: UNKNOWN
Platform: UNKNOWN
License-File: LICENSE
Requires-Dist: sparse-bundle-adjustment
Requires-Dist: numpy
Requires-Dist: tiny-tf
Requires-Dist: numba
Requires-Dist: scipy
Requires-Dist: scikit-image
Requires-Dist: tqdm
Requires-Dist: threeviz
